gitignore_cli/__init__.py
gitignore_cli/cli.py
gitignore_cli/generator.py
gitignore_cli/utils.py
gitignore_cli/gitignore/templates/1C-Bitrix.gitignore
gitignore_cli/gitignore/templates/1C.gitignore
gitignore_cli/gitignore/templates/A-Frame.gitignore
gitignore_cli/gitignore/templates/AL.gitignore
gitignore_cli/gitignore/templates/ASPNETCore.gitignore
gitignore_cli/gitignore/templates/ATE.gitignore
gitignore_cli/gitignore/templates/ATS.gitignore
gitignore_cli/gitignore/templates/AWR.gitignore
gitignore_cli/gitignore/templates/Actionscript.gitignore
gitignore_cli/gitignore/templates/Ada.gitignore
gitignore_cli/gitignore/templates/Adobe.gitignore
gitignore_cli/gitignore/templates/AdvancedInstaller.gitignore
gitignore_cli/gitignore/templates/AdventureGameStudio.gitignore
gitignore_cli/gitignore/templates/Agda.gitignore
gitignore_cli/gitignore/templates/AlteraQuartusII.gitignore
gitignore_cli/gitignore/templates/Altium.gitignore
gitignore_cli/gitignore/templates/Amplify.gitignore
gitignore_cli/gitignore/templates/Android.gitignore
gitignore_cli/gitignore/templates/AndroidStudio.gitignore
gitignore_cli/gitignore/templates/Angular.gitignore
gitignore_cli/gitignore/templates/Anjuta.gitignore
gitignore_cli/gitignore/templates/Ansible.gitignore
gitignore_cli/gitignore/templates/AnsibleTower.gitignore
gitignore_cli/gitignore/templates/ApacheCordova.gitignore
gitignore_cli/gitignore/templates/ApacheHadoop.gitignore
gitignore_cli/gitignore/templates/AppBuilder.gitignore
gitignore_cli/gitignore/templates/AppCode+all.gitignore
gitignore_cli/gitignore/templates/AppCode+iml.gitignore
gitignore_cli/gitignore/templates/AppCode.gitignore
gitignore_cli/gitignore/templates/AppEngine.gitignore
gitignore_cli/gitignore/templates/AppceleratorTitanium.gitignore
gitignore_cli/gitignore/templates/AptanaStudio.gitignore
gitignore_cli/gitignore/templates/Arcanist.gitignore
gitignore_cli/gitignore/templates/ArchLinuxPackages.gitignore
gitignore_cli/gitignore/templates/Archive.gitignore
gitignore_cli_py-0.1.3.dist-info/METADATA
gitignore_cli_py-0.1.3.dist-info/WHEEL
gitignore_cli_py-0.1.3.dist-info/entry_points.txt
gitignore_cli_py-0.1.3.dist-info/top_level.txt
gitignore_cli_py-0.1.3.dist-info/RECORD
