Metadata-Version: 2.1
Name: gitignore-cli-py
Version: 0.1.3
Summary: A command-line tool to generate .gitignore files from predefined templates
Home-page: https://github.com/ninjapythonbrasil/gitignore-cli-py
Author: Raphael Augusto Ferroni Cardoso
Author-email: rferronicardoso@gmail.com
License: MIT
Classifier: Development Status :: 4 - Beta
Classifier: Intended Audience :: Developers
Classifier: License :: OSI Approved :: MIT License
Classifier: Programming Language :: Python :: 3
Classifier: Programming Language :: Python :: 3.7
Classifier: Programming Language :: Python :: 3.8
Classifier: Programming Language :: Python :: 3.9
Classifier: Programming Language :: Python :: 3.10
Classifier: Topic :: Software Development :: Version Control
Requires-Python: >=3.8
Requires-Dist: click (>=8.0.0)
